aicsdaemon/__init__.py
aicsdaemon/daemon.py
aicsdaemon/example_child.py
aicsdaemon/types.py
aicsdaemon/bin/__init__.py
aicsdaemon/bin/my_example.py
aicsdaemon-0.1.0.dist-info/LICENSE
aicsdaemon-0.1.0.dist-info/METADATA
aicsdaemon-0.1.0.dist-info/WHEEL
aicsdaemon-0.1.0.dist-info/entry_points.txt
aicsdaemon-0.1.0.dist-info/top_level.txt
aicsdaemon-0.1.0.dist-info/RECORD
